{
  "project_info": {
    "project_number": "255034545471",
    "project_id": "flutter-places-2398",
    "storage_bucket": "flutter-places-2398.firebasestorage.app"
  },
  "client": [
    {
      "client_info": {
        "mobilesdk_app_id": "1:255034545471:android:db31ac50d5f7cfca766f8a",
        "android_client_info": {
          "package_name": "com.example.furka"
        }
      },
      "oauth_client": [
        {
          "client_id": "255034545471-dtifbo8vc704mj026b348tu1506ogflj.apps.googleusercontent.com",
          "client_type": 3
        }
      ],
      "api_key": [
        {
          "current_key": "AIzaSyAX9Pv1yp6L6QqCLt-n1Ex-t34BPfsJOdY"
        }
      ],
      "services": {
        "appinvite_service": {
          "other_platform_oauth_client": [
            {
              "client_id": "255034545471-dtifbo8vc704mj026b348tu1506ogflj.apps.googleusercontent.com",
              "client_type": 3
            },
            {
              "client_id": "255034545471-m113i62qcuei20laspq7uc0ngjm85e1j.apps.googleusercontent.com",
              "client_type": 2,
              "ios_info": {
                "bundle_id": "com.example.flutterNews"
              }
            }
          ]
        }
      }
    }
  ],
  "configuration_version": "1"
}